i18n_core/__init__.py
i18n_core/builtins.pyi
i18n_core/gui.py
i18n_core/patches.py
i18n_core/py.typed
i18n_core/registry.py
i18n_core/reset_locale.py
i18n_core-2.0.1.dist-info/METADATA
i18n_core-2.0.1.dist-info/WHEEL
i18n_core-2.0.1.dist-info/licenses/LICENSE
i18n_core-2.0.1.dist-info/RECORD
