Metadata-Version: 2.4
Name: i18n_core
Version: 2.0.1
Summary: Internationalization and localization setup and support utilities.
Author-email: Christopher Toth <q@q-continuum.net>
License-Expression: MIT
License-File: LICENSE
Classifier: Development Status :: 4 - Beta
Classifier: Intended Audience :: Developers
Classifier: Programming Language :: Python
Classifier: Topic :: Software Development :: Libraries
Requires-Dist: babel<3.0,>=2.15
Requires-Dist: platform-utils
Provides-Extra: dev
Requires-Dist: build; extra == 'dev'
Requires-Dist: pytest; extra == 'dev'
Requires-Dist: twine; extra == 'dev'
